validate_email.py
validate_email_wt-1.4.6.dist-info/AUTHORS
validate_email_wt-1.4.6.dist-info/LICENSE
validate_email_wt-1.4.6.dist-info/METADATA
validate_email_wt-1.4.6.dist-info/WHEEL
validate_email_wt-1.4.6.dist-info/top_level.txt
validate_email_wt-1.4.6.dist-info/RECORD
