Metadata-Version: 2.1
Name: validate-email-wt
Version: 1.4.6
Summary: validate_email verifies if an email address is valid and really exists.
Home-page: https://github.com/wtayyeb/validate_email
Author: w.Tayyeb
Author-email: w.tayyeb@gmail.com
License: LGPL
Keywords: email validation verification mx verify
Platform: UNKNOWN
Requires-Dist: disposable-email-domains
